drl_microgrid_ems/A3C_basic.py
drl_microgrid_ems/A3C_plusplus.py
drl_microgrid_ems/__init__.py
drl_microgrid_ems/tcl_env_dqn.py
drl_microgrid_ems/tcl_env_dqn_1.py
drl_microgrid_ems-0.1.1.dist-info/LICENSE
drl_microgrid_ems-0.1.1.dist-info/METADATA
drl_microgrid_ems-0.1.1.dist-info/WHEEL
drl_microgrid_ems-0.1.1.dist-info/top_level.txt
drl_microgrid_ems-0.1.1.dist-info/RECORD
