Metadata-Version: 2.1
Name: drl_microgrid_ems
Version: 0.1.1
Summary: Fork of  https://github.com/tahanakabi/DRL-for-microgrid-energy-management.git
Author-email: Rupert Young <rupert@perceptualrobots.com>
Classifier: Programming Language :: Python :: 3
Classifier: License :: OSI Approved :: MIT License
Classifier: Operating System :: OS Independent
Requires-Python: >=3.8
License-File: LICENSE
Requires-Dist: tqdm
Requires-Dist: scikit-learn
